[
  {
    "question": "What is ERP?",
    "type": "multiple_choice",
    "choice_a": "Inventory system",
    "choice_b": "Integrated business system",
    "choice_c": "Accounting tool",
    "choice_d": "Warehouse system",
    "correct_answer": "B",
    "explanation": "ERP integrates different business processes into one system.",
    "category": "SAP Basics",
    "difficulty": "easy"
  },
  {
    "question": "What does SAP ERP help companies do?",
    "type": "multiple_choice",
    "choice_a": "Separate business processes",
    "choice_b": "Integrate all business processes",
    "choice_c": "Only manage inventory",
    "choice_d": "Only create reports",
    "correct_answer": "B",
    "explanation": "SAP ERP connects different departments and processes.",
    "category": "SAP Basics",
    "difficulty": "easy"
  },
  {
    "question": "What does MM stand for in SAP?",
    "type": "multiple_choice",
    "choice_a": "Material Management",
    "choice_b": "Manufacturing Method",
    "choice_c": "Manual Movement",
    "choice_d": "Market Management",
    "correct_answer": "A",
    "explanation": "SAP MM means Materials Management.",
    "category": "SAP MM",
    "difficulty": "easy"
  },
  {
    "question": "What is the main purpose of SAP MM?",
    "type": "multiple_choice",
    "choice_a": "Payroll processing",
    "choice_b": "Procurement and inventory management",
    "choice_c": "Customer service",
    "choice_d": "Employee attendance",
    "correct_answer": "B",
    "explanation": "SAP MM handles purchasing, materials, and inventory.",
    "category": "SAP MM",
    "difficulty": "easy"
  },
  {
    "question": "What transaction code is used to create a Purchase Order?",
    "type": "multiple_choice",
    "choice_a": "MM01",
    "choice_b": "ME21N",
    "choice_c": "MB51",
    "choice_d": "MMBE",
    "correct_answer": "B",
    "explanation": "ME21N is used to create a Purchase Order.",
    "category": "Transaction Codes",
    "difficulty": "easy"
  },
  {
    "question": "What transaction code is used to create material master data?",
    "type": "multiple_choice",
    "choice_a": "MM01",
    "choice_b": "MI01",
    "choice_c": "MIRO",
    "choice_d": "MIGO",
    "correct_answer": "A",
    "explanation": "MM01 is used to create material master data.",
    "category": "Transaction Codes",
    "difficulty": "easy"
  },
  {
    "question": "What transaction code is used for goods movement?",
    "type": "multiple_choice",
    "choice_a": "ME21N",
    "choice_b": "MIGO",
    "choice_c": "MB52",
    "choice_d": "MM01",
    "correct_answer": "B",
    "explanation": "MIGO is used for goods receipt, goods issue, and other goods movements.",
    "category": "Transaction Codes",
    "difficulty": "easy"
  },
  {
    "question": "What movement type is used for initial stock entry?",
    "type": "multiple_choice",
    "choice_a": "561",
    "choice_b": "562",
    "choice_c": "101",
    "choice_d": "102",
    "correct_answer": "A",
    "explanation": "Movement type 561 is used to add initial stock.",
    "category": "Movement Types",
    "difficulty": "easy"
  },
  {
    "question": "What movement type is used to reverse movement type 561?",
    "type": "multiple_choice",
    "choice_a": "101",
    "choice_b": "102",
    "choice_c": "562",
    "choice_d": "501",
    "correct_answer": "C",
    "explanation": "Movement type 562 reverses the stock posted using 561.",
    "category": "Movement Types",
    "difficulty": "easy"
  },
  {
    "question": "What transaction code shows stock overview?",
    "type": "multiple_choice",
    "choice_a": "MMBE",
    "choice_b": "ME21N",
    "choice_c": "MIRO",
    "choice_d": "MM01",
    "correct_answer": "A",
    "explanation": "MMBE shows stock overview by material, plant, and storage location.",
    "category": "Transaction Codes",
    "difficulty": "easy"
  },
  {
    "question": "What transaction code shows stock report?",
    "type": "multiple_choice",
    "choice_a": "MB52",
    "choice_b": "ME21N",
    "choice_c": "MI01",
    "choice_d": "MIRO",
    "correct_answer": "A",
    "explanation": "MB52 displays stock reports.",
    "category": "Transaction Codes",
    "difficulty": "easy"
  },
  {
    "question": "What transaction code shows material movement history?",
    "type": "multiple_choice",
    "choice_a": "MB51",
    "choice_b": "MB52",
    "choice_c": "MMBE",
    "choice_d": "MM01",
    "correct_answer": "A",
    "explanation": "MB51 shows material document history.",
    "category": "Transaction Codes",
    "difficulty": "easy"
  },
  {
    "question": "What is unrestricted stock?",
    "type": "multiple_choice",
    "choice_a": "Stock that cannot be used",
    "choice_b": "Stock ready for use or sale",
    "choice_c": "Stock under inspection",
    "choice_d": "Stock already deleted",
    "correct_answer": "B",
    "explanation": "Unrestricted stock is available for use or selling.",
    "category": "Inventory",
    "difficulty": "easy"
  },
  {
    "question": "What is quality inspection stock?",
    "type": "multiple_choice",
    "choice_a": "Stock ready to sell",
    "choice_b": "Stock that needs to be checked",
    "choice_c": "Stock already consumed",
    "choice_d": "Stock for accounting only",
    "correct_answer": "B",
    "explanation": "Quality inspection stock must be inspected before use.",
    "category": "Inventory",
    "difficulty": "easy"
  },
  {
    "question": "What is blocked stock?",
    "type": "multiple_choice",
    "choice_a": "Stock ready for sale",
    "choice_b": "Stock not available for use or sale",
    "choice_c": "Stock in transit only",
    "choice_d": "Stock with no value",
    "correct_answer": "B",
    "explanation": "Blocked stock cannot be used or sold.",
    "category": "Inventory",
    "difficulty": "easy"
  },
  {
    "question": "What transaction code is used to initialize physical inventory count?",
    "type": "multiple_choice",
    "choice_a": "MI01",
    "choice_b": "MIRO",
    "choice_c": "MIGO",
    "choice_d": "ME21N",
    "correct_answer": "A",
    "explanation": "MI01 is used to create or initialize a physical inventory document.",
    "category": "Physical Inventory",
    "difficulty": "easy"
  },
  {
    "question": "What does freeze mean in inventory?",
    "type": "multiple_choice",
    "choice_a": "Inventory can still move",
    "choice_b": "Inventory movement is restricted",
    "choice_c": "Inventory is deleted",
    "choice_d": "Inventory is sold",
    "correct_answer": "B",
    "explanation": "Freeze means inventory movement is restricted during counting.",
    "category": "Physical Inventory",
    "difficulty": "medium"
  },
  {
    "question": "What does posting block mean?",
    "type": "multiple_choice",
    "choice_a": "Can sell but cannot post",
    "choice_b": "Can post but cannot sell",
    "choice_c": "Can delete stock",
    "choice_d": "Can create vendor",
    "correct_answer": "B",
    "explanation": "Posting block allows posting but prevents selling.",
    "category": "Physical Inventory",
    "difficulty": "medium"
  },
  {
    "question": "What is forecasting?",
    "type": "multiple_choice",
    "choice_a": "Predicting future demand",
    "choice_b": "Creating invoices",
    "choice_c": "Counting stock",
    "choice_d": "Creating vendors",
    "correct_answer": "A",
    "explanation": "Forecasting means predicting future demand.",
    "category": "Planning",
    "difficulty": "easy"
  },
  {
    "question": "What is rough-cut capacity planning?",
    "type": "multiple_choice",
    "choice_a": "Checking if resources can meet demand",
    "choice_b": "Creating stock reports",
    "choice_c": "Posting invoices",
    "choice_d": "Creating vendors",
    "correct_answer": "A",
    "explanation": "Rough-cut capacity planning checks resource availability.",
    "category": "Planning",
    "difficulty": "medium"
  },
  {
    "question": "What is a Purchase Requisition?",
    "type": "multiple_choice",
    "choice_a": "External order to vendor",
    "choice_b": "Internal request to procure materials",
    "choice_c": "Invoice document",
    "choice_d": "Stock report",
    "correct_answer": "B",
    "explanation": "A purchase requisition is an internal request for materials.",
    "category": "SAP MM",
    "difficulty": "easy"
  },
  {
    "question": "What happens after a Purchase Order is created?",
    "type": "multiple_choice",
    "choice_a": "Invoice is posted immediately",
    "choice_b": "Goods Receipt is performed",
    "choice_c": "Vendor is deleted",
    "choice_d": "Stock is blocked",
    "correct_answer": "B",
    "explanation": "After PO, goods are received using MIGO.",
    "category": "Procurement Process",
    "difficulty": "easy"
  },
  {
    "question": "What transaction is used for invoice verification?",
    "type": "multiple_choice",
    "choice_a": "MIGO",
    "choice_b": "MIRO",
    "choice_c": "MB51",
    "choice_d": "MM01",
    "correct_answer": "B",
    "explanation": "MIRO is used to post vendor invoices.",
    "category": "Transaction Codes",
    "difficulty": "easy"
  },
  {
    "question": "What is Goods Receipt?",
    "type": "multiple_choice",
    "choice_a": "Sending goods to vendor",
    "choice_b": "Receiving goods into inventory",
    "choice_c": "Deleting stock",
    "choice_d": "Creating invoice",
    "correct_answer": "B",
    "explanation": "Goods Receipt updates stock after receiving items.",
    "category": "SAP MM",
    "difficulty": "easy"
  },
  {
    "question": "What is the purpose of MIGO?",
    "type": "multiple_choice",
    "choice_a": "Create PO",
    "choice_b": "Manage goods movement",
    "choice_c": "Create vendor",
    "choice_d": "Create report",
    "correct_answer": "B",
    "explanation": "MIGO handles goods receipt, issue, and transfer.",
    "category": "Transaction Codes",
    "difficulty": "easy"
  },
  {
    "question": "What is master data?",
    "type": "multiple_choice",
    "choice_a": "Temporary data",
    "choice_b": "Permanent data used repeatedly",
    "choice_c": "Deleted data",
    "choice_d": "Financial data only",
    "correct_answer": "B",
    "explanation": "Master data is reused across transactions.",
    "category": "SAP Basics",
    "difficulty": "easy"
  },
  {
    "question": "What is transaction data?",
    "type": "multiple_choice",
    "choice_a": "Permanent data",
    "choice_b": "Temporary process data",
    "choice_c": "Vendor data",
    "choice_d": "Material data",
    "correct_answer": "B",
    "explanation": "Transaction data is created during operations.",
    "category": "SAP Basics",
    "difficulty": "easy"
  },
  {
    "question": "What is the purpose of MB51?",
    "type": "multiple_choice",
    "choice_a": "View stock",
    "choice_b": "View movement history",
    "choice_c": "Create PO",
    "choice_d": "Create invoice",
    "correct_answer": "B",
    "explanation": "MB51 shows material movement history.",
    "category": "Transaction Codes",
    "difficulty": "easy"
  },
  {
    "question": "What is the purpose of MB52?",
    "type": "multiple_choice",
    "choice_a": "View stock report",
    "choice_b": "Create invoice",
    "choice_c": "Create vendor",
    "choice_d": "Count inventory",
    "correct_answer": "A",
    "explanation": "MB52 shows stock reports.",
    "category": "Transaction Codes",
    "difficulty": "easy"
  },
  {
    "question": "What is the purpose of MMBE?",
    "type": "multiple_choice",
    "choice_a": "Vendor report",
    "choice_b": "Stock overview",
    "choice_c": "Invoice posting",
    "choice_d": "PO creation",
    "correct_answer": "B",
    "explanation": "MMBE shows stock by plant/storage.",
    "category": "Transaction Codes",
    "difficulty": "easy"
  },
  {
    "question": "What does a Standard PO mean?",
    "type": "multiple_choice",
    "choice_a": "With shipping",
    "choice_b": "Without shipping details",
    "choice_c": "With invoice",
    "choice_d": "With vendor deletion",
    "correct_answer": "B",
    "explanation": "Standard PO usually has no shipping conditions.",
    "category": "Procurement",
    "difficulty": "medium"
  },
  {
    "question": "What is a Sales Organization?",
    "type": "multiple_choice",
    "choice_a": "Warehouse unit",
    "choice_b": "Structure for sales activities",
    "choice_c": "Inventory group",
    "choice_d": "Vendor group",
    "correct_answer": "B",
    "explanation": "Sales Org handles sales processes.",
    "category": "Sales Concepts",
    "difficulty": "medium"
  },
  {
    "question": "What is Distribution Channel?",
    "type": "multiple_choice",
    "choice_a": "Storage type",
    "choice_b": "Way goods reach customers",
    "choice_c": "Inventory report",
    "choice_d": "Vendor type",
    "correct_answer": "B",
    "explanation": "It defines how products are distributed.",
    "category": "Sales Concepts",
    "difficulty": "medium"
  },
  {
    "question": "What is a Vendor?",
    "type": "multiple_choice",
    "choice_a": "Customer",
    "choice_b": "Supplier of goods/services",
    "choice_c": "Employee",
    "choice_d": "Manager",
    "correct_answer": "B",
    "explanation": "Vendor supplies materials or services.",
    "category": "SAP MM",
    "difficulty": "easy"
  },
  {
    "question": "What is Inventory Management?",
    "type": "multiple_choice",
    "choice_a": "Managing employees",
    "choice_b": "Managing stock and materials",
    "choice_c": "Managing invoices",
    "choice_d": "Managing reports",
    "correct_answer": "B",
    "explanation": "Inventory management tracks stock levels.",
    "category": "SAP MM",
    "difficulty": "easy"
  },
  {
    "question": "What is Goods Issue?",
    "type": "multiple_choice",
    "choice_a": "Receiving goods",
    "choice_b": "Sending goods out",
    "choice_c": "Creating invoice",
    "choice_d": "Blocking stock",
    "correct_answer": "B",
    "explanation": "Goods issue removes stock from inventory.",
    "category": "SAP MM",
    "difficulty": "easy"
  },
  {
    "question": "What happens during invoice verification?",
    "type": "multiple_choice",
    "choice_a": "Stock is updated",
    "choice_b": "Invoice is matched with PO and GR",
    "choice_c": "Vendor is deleted",
    "choice_d": "Material is created",
    "correct_answer": "B",
    "explanation": "Invoice is checked against PO and GR.",
    "category": "SAP MM",
    "difficulty": "medium"
  },
  {
    "question": "What is the purpose of forecasting?",
    "type": "multiple_choice",
    "choice_a": "Create vendor",
    "choice_b": "Predict demand",
    "choice_c": "Delete stock",
    "choice_d": "Create report",
    "correct_answer": "B",
    "explanation": "Forecasting helps predict demand.",
    "category": "Planning",
    "difficulty": "easy"
  },
  {
    "question": "What is bottleneck in production?",
    "type": "multiple_choice",
    "choice_a": "Fast process",
    "choice_b": "Delay due to limited resources",
    "choice_c": "Inventory increase",
    "choice_d": "Vendor issue",
    "correct_answer": "B",
    "explanation": "Bottleneck slows down production.",
    "category": "Planning",
    "difficulty": "medium"
  },
  {
    "question": "What is integration in SAP?",
    "type": "multiple_choice",
    "choice_a": "Separate systems",
    "choice_b": "Connected processes",
    "choice_c": "Manual work",
    "choice_d": "Vendor link",
    "correct_answer": "B",
    "explanation": "Integration connects all modules.",
    "category": "SAP Basics",
    "difficulty": "easy"
  },
  {
    "question": "What is the Development (DEV) system?",
    "type": "multiple_choice",
    "choice_a": "Used for daily transactions",
    "choice_b": "Used for testing only",
    "choice_c": "Used for creating and maintaining objects",
    "choice_d": "Used for reporting",
    "correct_answer": "C",
    "explanation": "DEV is used for creating and maintaining system objects.",
    "category": "SAP Systems",
    "difficulty": "easy"
  },
  {
    "question": "What is the purpose of the Quality Assurance (QAS) system?",
    "type": "multiple_choice",
    "choice_a": "Production use",
    "choice_b": "Testing environment",
    "choice_c": "Development environment",
    "choice_d": "Reporting system",
    "correct_answer": "B",
    "explanation": "QAS is used for testing such as UAT and integration tests.",
    "category": "SAP Systems",
    "difficulty": "easy"
  },
  {
    "question": "What is the Production (PRD) system used for?",
    "type": "multiple_choice",
    "choice_a": "Testing",
    "choice_b": "Development",
    "choice_c": "Daily business operations",
    "choice_d": "Training only",
    "correct_answer": "C",
    "explanation": "PRD is where actual business transactions occur.",
    "category": "SAP Systems",
    "difficulty": "easy"
  },
  {
    "question": "What is customization in SAP?",
    "type": "multiple_choice",
    "choice_a": "Using standard SAP only",
    "choice_b": "Changing SAP to meet business needs",
    "choice_c": "Deleting data",
    "choice_d": "Creating reports only",
    "correct_answer": "B",
    "explanation": "Customization modifies SAP to fit business requirements.",
    "category": "SAP Concepts",
    "difficulty": "medium"
  },
  {
    "question": "What does customization address?",
    "type": "multiple_choice",
    "choice_a": "FIT",
    "choice_b": "GAP",
    "choice_c": "REPORT",
    "choice_d": "DATA",
    "correct_answer": "B",
    "explanation": "Customization is used when there is a GAP.",
    "category": "SAP Concepts",
    "difficulty": "medium"
  },
  {
    "question": "What is configuration in SAP?",
    "type": "multiple_choice",
    "choice_a": "Custom coding",
    "choice_b": "Mapping business process using standard SAP",
    "choice_c": "Deleting data",
    "choice_d": "Reporting",
    "correct_answer": "B",
    "explanation": "Configuration aligns business processes with SAP standards.",
    "category": "SAP Concepts",
    "difficulty": "medium"
  },
  {
    "question": "What does configuration address?",
    "type": "multiple_choice",
    "choice_a": "GAP",
    "choice_b": "FIT",
    "choice_c": "REPORT",
    "choice_d": "ERROR",
    "correct_answer": "B",
    "explanation": "Configuration addresses a FIT.",
    "category": "SAP Concepts",
    "difficulty": "medium"
  },
  {
    "question": "What is centrally stored master data?",
    "type": "multiple_choice",
    "choice_a": "Duplicate data",
    "choice_b": "Consistent and updated data",
    "choice_c": "Temporary data",
    "choice_d": "Old data",
    "correct_answer": "B",
    "explanation": "It is consistent, updated, and non-redundant data.",
    "category": "SAP Basics",
    "difficulty": "easy"
  },
  {
    "question": "What are transactions in SAP?",
    "type": "multiple_choice",
    "choice_a": "Reports",
    "choice_b": "Applications executing business processes",
    "choice_c": "Master data",
    "choice_d": "Vendors",
    "correct_answer": "B",
    "explanation": "Transactions execute processes.",
    "category": "SAP Basics",
    "difficulty": "easy"
  },
  {
    "question": "What is a document in SAP?",
    "type": "multiple_choice",
    "choice_a": "Report file",
    "choice_b": "Record of a transaction",
    "choice_c": "Vendor file",
    "choice_d": "Inventory list",
    "correct_answer": "B",
    "explanation": "Documents store transaction details.",
    "category": "SAP Basics",
    "difficulty": "easy"
  },
  {
    "question": "Which are primary operational activities?",
    "type": "multiple_choice",
    "choice_a": "Sales, Procurement, Production",
    "choice_b": "HR, Finance, IT",
    "choice_c": "Marketing, Sales",
    "choice_d": "Storage only",
    "correct_answer": "A",
    "explanation": "These are core business operations.",
    "category": "SAP Basics",
    "difficulty": "easy"
  },
  {
    "question": "Which are secondary activities?",
    "type": "multiple_choice",
    "choice_a": "Sales only",
    "choice_b": "Quality, Maintenance, Warehouse",
    "choice_c": "Procurement only",
    "choice_d": "Production only",
    "correct_answer": "B",
    "explanation": "These support main processes.",
    "category": "SAP Basics",
    "difficulty": "medium"
  },
  {
    "question": "What is a Sales Order?",
    "type": "multiple_choice",
    "choice_a": "Vendor request",
    "choice_b": "Customer purchase request",
    "choice_c": "Inventory report",
    "choice_d": "Invoice",
    "correct_answer": "B",
    "explanation": "Sales order confirms customer purchase.",
    "category": "Sales",
    "difficulty": "easy"
  },
  {
    "question": "What is CRM?",
    "type": "multiple_choice",
    "choice_a": "Customer Resource Model",
    "choice_b": "Customer Relationship Management",
    "choice_c": "Cost Report Model",
    "choice_d": "Customer Record Management",
    "correct_answer": "B",
    "explanation": "CRM focuses on customer relationships.",
    "category": "SAP Concepts",
    "difficulty": "easy"
  },
  {
    "question": "What is the goal of CRM?",
    "type": "multiple_choice",
    "choice_a": "Reduce cost",
    "choice_b": "Build long-term relationships",
    "choice_c": "Increase stock",
    "choice_d": "Manage reports",
    "correct_answer": "B",
    "explanation": "CRM builds long-term customer relationships.",
    "category": "SAP Concepts",
    "difficulty": "easy"
  },
  {
    "question": "What is pre-sales activity?",
    "type": "multiple_choice",
    "choice_a": "Invoice creation",
    "choice_b": "Inquiry or quotation",
    "choice_c": "Goods receipt",
    "choice_d": "Stock report",
    "correct_answer": "B",
    "explanation": "Pre-sales includes inquiries and quotations.",
    "category": "Sales",
    "difficulty": "medium"
  },
  {
    "question": "What can a sales order use as reference?",
    "type": "multiple_choice",
    "choice_a": "Vendor data",
    "choice_b": "Pre-sales documents",
    "choice_c": "Inventory",
    "choice_d": "Reports",
    "correct_answer": "B",
    "explanation": "Sales orders can use quotations/inquiries.",
    "category": "Sales",
    "difficulty": "medium"
  },
  {
    "question": "What is production planning?",
    "type": "multiple_choice",
    "choice_a": "Inventory tracking",
    "choice_b": "Managing production processes",
    "choice_c": "Vendor creation",
    "choice_d": "Invoice posting",
    "correct_answer": "B",
    "explanation": "PP handles production planning and control.",
    "category": "SAP PP",
    "difficulty": "easy"
  },
  {
    "question": "Why is SAP ERP important?",
    "type": "multiple_choice",
    "choice_a": "It separates processes",
    "choice_b": "It integrates processes",
    "choice_c": "It deletes data",
    "choice_d": "It only reports",
    "correct_answer": "B",
    "explanation": "SAP ERP connects all processes.",
    "category": "SAP Basics",
    "difficulty": "easy"
  },
  {
    "question": "What are forecast models?",
    "type": "multiple_choice",
    "choice_a": "Reports",
    "choice_b": "Methods to estimate demand",
    "choice_c": "Vendors",
    "choice_d": "Stock types",
    "correct_answer": "B",
    "explanation": "Forecast models estimate demand.",
    "category": "Planning",
    "difficulty": "easy"
  },
  {
    "question": "What is forecast adjustment?",
    "type": "multiple_choice",
    "choice_a": "Delete forecast",
    "choice_b": "Manually change forecast",
    "choice_c": "Ignore forecast",
    "choice_d": "Freeze forecast",
    "correct_answer": "B",
    "explanation": "Forecast values can be adjusted.",
    "category": "Planning",
    "difficulty": "easy"
  },
  {
    "question": "What is seasonal influence?",
    "type": "multiple_choice",
    "choice_a": "Vendor issue",
    "choice_b": "Demand changes by season",
    "choice_c": "Stock issue",
    "choice_d": "Report issue",
    "correct_answer": "B",
    "explanation": "Demand varies depending on season.",
    "category": "Planning",
    "difficulty": "easy"
  },
  {
    "question": "What is marketing promotion impact?",
    "type": "multiple_choice",
    "choice_a": "Vendor change",
    "choice_b": "Sales events affecting demand",
    "choice_c": "Stock deletion",
    "choice_d": "Report change",
    "correct_answer": "B",
    "explanation": "Promotions affect demand forecast.",
    "category": "Planning",
    "difficulty": "easy"
  },
  {
    "question": "What is forecast revision?",
    "type": "multiple_choice",
    "choice_a": "Deleting forecast",
    "choice_b": "Updating forecast",
    "choice_c": "Ignoring forecast",
    "choice_d": "Blocking forecast",
    "correct_answer": "B",
    "explanation": "Forecasts are updated regularly.",
    "category": "Planning",
    "difficulty": "easy"
  },
  {
    "question": "What is the purpose of DEV, QAS, and PRD in SAP?",
    "type": "multiple_choice",
    "choice_a": "Inventory levels",
    "choice_b": "System landscape environments",
    "choice_c": "Vendor management",
    "choice_d": "Reporting tools",
    "correct_answer": "B",
    "explanation": "DEV, QAS, and PRD are system environments.",
    "category": "SAP Systems",
    "difficulty": "medium"
  },
  {
    "question": "Which system is used for testing before production?",
    "type": "multiple_choice",
    "choice_a": "DEV",
    "choice_b": "QAS",
    "choice_c": "PRD",
    "choice_d": "MM",
    "correct_answer": "B",
    "explanation": "QAS is used for testing.",
    "category": "SAP Systems",
    "difficulty": "easy"
  },
  {
    "question": "Which system is used for real transactions?",
    "type": "multiple_choice",
    "choice_a": "DEV",
    "choice_b": "QAS",
    "choice_c": "PRD",
    "choice_d": "TEST",
    "correct_answer": "C",
    "explanation": "PRD is used for daily operations.",
    "category": "SAP Systems",
    "difficulty": "easy"
  },
  {
    "question": "What is the difference between configuration and customization?",
    "type": "multiple_choice",
    "choice_a": "No difference",
    "choice_b": "Configuration uses standard SAP, customization modifies it",
    "choice_c": "Customization uses standard SAP only",
    "choice_d": "Configuration deletes data",
    "correct_answer": "B",
    "explanation": "Configuration = FIT, Customization = GAP.",
    "category": "SAP Concepts",
    "difficulty": "medium"
  },
  {
    "question": "What is a GAP in SAP?",
    "type": "multiple_choice",
    "choice_a": "When SAP fits perfectly",
    "choice_b": "When SAP standard does not meet requirements",
    "choice_c": "When system is deleted",
    "choice_d": "When data is duplicated",
    "correct_answer": "B",
    "explanation": "GAP requires customization.",
    "category": "SAP Concepts",
    "difficulty": "medium"
  },
  {
    "question": "What is a FIT in SAP?",
    "type": "multiple_choice",
    "choice_a": "When SAP standard meets requirements",
    "choice_b": "When SAP fails",
    "choice_c": "When data is missing",
    "choice_d": "When system crashes",
    "correct_answer": "A",
    "explanation": "FIT means standard SAP works.",
    "category": "SAP Concepts",
    "difficulty": "medium"
  },
  {
    "question": "Why is master data important?",
    "type": "multiple_choice",
    "choice_a": "It is temporary",
    "choice_b": "It is reused across transactions",
    "choice_c": "It is deleted often",
    "choice_d": "It is only for reports",
    "correct_answer": "B",
    "explanation": "Master data supports transactions.",
    "category": "SAP Basics",
    "difficulty": "easy"
  },
  {
    "question": "What makes master data “centralized”?",
    "type": "multiple_choice",
    "choice_a": "Stored in different systems",
    "choice_b": "Stored once and shared across modules",
    "choice_c": "Stored temporarily",
    "choice_d": "Stored manually",
    "correct_answer": "B",
    "explanation": "Centralized data is shared across SAP.",
    "category": "SAP Basics",
    "difficulty": "easy"
  },
  {
    "question": "What is an example of transaction data?",
    "type": "multiple_choice",
    "choice_a": "Material master",
    "choice_b": "Vendor master",
    "choice_c": "Purchase Order",
    "choice_d": "Company code",
    "correct_answer": "C",
    "explanation": "PO is transaction data.",
    "category": "SAP Basics",
    "difficulty": "easy"
  },
  {
    "question": "What is Sales Order Processing?",
    "type": "multiple_choice",
    "choice_a": "Managing vendors",
    "choice_b": "Managing sales transactions",
    "choice_c": "Managing inventory only",
    "choice_d": "Managing HR",
    "correct_answer": "B",
    "explanation": "It covers full sales cycle.",
    "category": "Sales",
    "difficulty": "medium"
  },
  {
    "question": "What is the first step in sales process?",
    "type": "multiple_choice",
    "choice_a": "Invoice",
    "choice_b": "Pre-sales activity",
    "choice_c": "Delivery",
    "choice_d": "Payment",
    "correct_answer": "B",
    "explanation": "Pre-sales starts the process.",
    "category": "Sales",
    "difficulty": "easy"
  },
  {
    "question": "What happens after sales order?",
    "type": "multiple_choice",
    "choice_a": "Delivery and invoicing",
    "choice_b": "Vendor creation",
    "choice_c": "Inventory deletion",
    "choice_d": "System shutdown",
    "correct_answer": "A",
    "explanation": "Sales continues to fulfillment.",
    "category": "Sales",
    "difficulty": "medium"
  },
  {
    "question": "What is the goal of “Keeping the customer”?",
    "type": "multiple_choice",
    "choice_a": "Reduce cost",
    "choice_b": "Build loyalty",
    "choice_c": "Increase inventory",
    "choice_d": "Delete accounts",
    "correct_answer": "B",
    "explanation": "Customer retention builds loyalty.",
    "category": "CRM",
    "difficulty": "easy"
  },
  {
    "question": "What is “Gaining the customer”?",
    "type": "multiple_choice",
    "choice_a": "First contact",
    "choice_b": "Customer purchase intent",
    "choice_c": "Invoice stage",
    "choice_d": "Delivery stage",
    "correct_answer": "B",
    "explanation": "Customer is ready to buy.",
    "category": "CRM",
    "difficulty": "medium"
  },
  {
    "question": "What is “Service” in CRM?",
    "type": "multiple_choice",
    "choice_a": "Selling products only",
    "choice_b": "Ensuring customer satisfaction",
    "choice_c": "Deleting customer",
    "choice_d": "Creating reports",
    "correct_answer": "B",
    "explanation": "Service ensures satisfaction.",
    "category": "CRM",
    "difficulty": "easy"
  },
  {
    "question": "What is the benefit of End-to-End Process?",
    "type": "multiple_choice",
    "choice_a": "Separate processes",
    "choice_b": "Full process visibility",
    "choice_c": "Manual work",
    "choice_d": "Limited data",
    "correct_answer": "B",
    "explanation": "End-to-end integrates all steps.",
    "category": "SAP Basics",
    "difficulty": "easy"
  },
  {
    "question": "What is manufacturing activity?",
    "type": "multiple_choice",
    "choice_a": "Inventory only",
    "choice_b": "Producing goods from planning to output",
    "choice_c": "Vendor creation",
    "choice_d": "Reporting",
    "correct_answer": "B",
    "explanation": "Manufacturing covers full production.",
    "category": "SAP PP",
    "difficulty": "easy"
  },
  {
    "question": "Why is real-time data important?",
    "type": "multiple_choice",
    "choice_a": "Delayed updates",
    "choice_b": "Instant decision-making",
    "choice_c": "Manual tracking",
    "choice_d": "Data deletion",
    "correct_answer": "B",
    "explanation": "Real-time improves decisions.",
    "category": "SAP Basics",
    "difficulty": "easy"
  },
  {
    "question": "What is demand management?",
    "type": "multiple_choice",
    "choice_a": "Vendor tracking",
    "choice_b": "Managing customer demand",
    "choice_c": "Stock deletion",
    "choice_d": "HR process",
    "correct_answer": "B",
    "explanation": "Demand management controls demand.",
    "category": "Planning",
    "difficulty": "easy"
  },
  {
    "question": "What is planning level forecasting?",
    "type": "multiple_choice",
    "choice_a": "Detailed level",
    "choice_b": "High-level demand",
    "choice_c": "Inventory level",
    "choice_d": "Vendor level",
    "correct_answer": "B",
    "explanation": "Planning level is general forecast.",
    "category": "Planning",
    "difficulty": "medium"
  },
  {
    "question": "What is detailed level forecasting?",
    "type": "multiple_choice",
    "choice_a": "High-level",
    "choice_b": "Per product",
    "choice_c": "Per vendor",
    "choice_d": "Per report",
    "correct_answer": "B",
    "explanation": "Detailed level focuses on product.",
    "category": "Planning",
    "difficulty": "medium"
  },
  {
    "question": "What happens during forecast transfer?",
    "type": "multiple_choice",
    "choice_a": "Deleted data",
    "choice_b": "Sent to demand management/MPS",
    "choice_c": "Vendor update",
    "choice_d": "Inventory count",
    "correct_answer": "B",
    "explanation": "Forecast goes to production planning.",
    "category": "Planning",
    "difficulty": "medium"
  },
  {
    "question": "What is the role of MPS?",
    "type": "multiple_choice",
    "choice_a": "Stock counting",
    "choice_b": "Detailed production scheduling",
    "choice_c": "Vendor creation",
    "choice_d": "Invoice posting",
    "correct_answer": "B",
    "explanation": "MPS plans production.",
    "category": "Planning",
    "difficulty": "medium"
  },
  {
    "question": "What is a supply network?",
    "type": "multiple_choice",
    "choice_a": "Single system",
    "choice_b": "Connected organizations and processes",
    "choice_c": "Inventory report",
    "choice_d": "Vendor list",
    "correct_answer": "B",
    "explanation": "Supply network links processes.",
    "category": "SAP Basics",
    "difficulty": "medium"
  },
  {
    "question": "What is the first step in the procurement process?",
    "type": "multiple_choice",
    "choice_a": "Purchase Order",
    "choice_b": "Goods Receipt",
    "choice_c": "Purchase Requisition",
    "choice_d": "Invoice Verification",
    "correct_answer": "C",
    "explanation": "Procurement starts with a Purchase Requisition.",
    "category": "Procurement",
    "difficulty": "easy"
  },
  {
    "question": "What document is sent to the vendor to request goods?",
    "type": "multiple_choice",
    "choice_a": "Invoice",
    "choice_b": "Purchase Order",
    "choice_c": "Goods Receipt",
    "choice_d": "Material Document",
    "correct_answer": "B",
    "explanation": "PO is sent to vendor.",
    "category": "Procurement",
    "difficulty": "easy"
  },
  {
    "question": "Which transaction is used for Goods Receipt?",
    "type": "multiple_choice",
    "choice_a": "MIRO",
    "choice_b": "ME21N",
    "choice_c": "MIGO",
    "choice_d": "MB51",
    "correct_answer": "C",
    "explanation": "MIGO handles goods receipt.",
    "category": "Transaction Codes",
    "difficulty": "easy"
  },
  {
    "question": "What happens during Goods Receipt?",
    "type": "multiple_choice",
    "choice_a": "Invoice is created",
    "choice_b": "Stock is updated",
    "choice_c": "Vendor is created",
    "choice_d": "PO is deleted",
    "correct_answer": "B",
    "explanation": "Stock increases after GR.",
    "category": "SAP MM",
    "difficulty": "easy"
  },
  {
    "question": "What is checked during Invoice Verification?",
    "type": "multiple_choice",
    "choice_a": "Employee data",
    "choice_b": "PO and GR match",
    "choice_c": "Vendor address",
    "choice_d": "Material type",
    "correct_answer": "B",
    "explanation": "Invoice is matched with PO and GR.",
    "category": "SAP MM",
    "difficulty": "medium"
  },
  {
    "question": "What is the correct sequence of procurement?",
    "type": "multiple_choice",
    "choice_a": "PO → PR → GR → Invoice",
    "choice_b": "PR → PO → GR → Invoice",
    "choice_c": "GR → PR → PO → Invoice",
    "choice_d": "Invoice → PR → PO → GR",
    "correct_answer": "B",
    "explanation": "Standard flow.",
    "category": "Procurement",
    "difficulty": "easy"
  },
  {
    "question": "What is the purpose of SAP MM?",
    "type": "multiple_choice",
    "choice_a": "Manage HR",
    "choice_b": "Manage materials and procurement",
    "choice_c": "Manage finance",
    "choice_d": "Manage marketing",
    "correct_answer": "B",
    "explanation": "MM handles materials.",
    "category": "SAP MM",
    "difficulty": "easy"
  },
  {
    "question": "What type of data is reused across transactions?",
    "type": "multiple_choice",
    "choice_a": "Transaction data",
    "choice_b": "Master data",
    "choice_c": "Temporary data",
    "choice_d": "Report data",
    "correct_answer": "B",
    "explanation": "Master data is reusable.",
    "category": "SAP Basics",
    "difficulty": "easy"
  },
  {
    "question": "What type of data is created during processes?",
    "type": "multiple_choice",
    "choice_a": "Master data",
    "choice_b": "Transaction data",
    "choice_c": "Static data",
    "choice_d": "Archived data",
    "correct_answer": "B",
    "explanation": "Transaction data is temporary.",
    "category": "SAP Basics",
    "difficulty": "easy"
  },
  {
    "question": "What is the role of ME21N?",
    "type": "multiple_choice",
    "choice_a": "Create invoice",
    "choice_b": "Create PO",
    "choice_c": "Create material",
    "choice_d": "Create report",
    "correct_answer": "B",
    "explanation": "ME21N creates PO.",
    "category": "Transaction Codes",
    "difficulty": "easy"
  },
  {
    "question": "What is the role of MIRO?",
    "type": "multiple_choice",
    "choice_a": "Goods receipt",
    "choice_b": "Invoice posting",
    "choice_c": "Stock overview",
    "choice_d": "Material creation",
    "correct_answer": "B",
    "explanation": "MIRO is for invoice verification.",
    "category": "Transaction Codes",
    "difficulty": "easy"
  },
  {
    "question": "What is the role of MM01?",
    "type": "multiple_choice",
    "choice_a": "Create PO",
    "choice_b": "Create material",
    "choice_c": "Create report",
    "choice_d": "Create invoice",
    "correct_answer": "B",
    "explanation": "MM01 creates material master.",
    "category": "Transaction Codes",
    "difficulty": "easy"
  },
  {
    "question": "What is the role of MI01?",
    "type": "multiple_choice",
    "choice_a": "Invoice",
    "choice_b": "Inventory count",
    "choice_c": "PO creation",
    "choice_d": "Vendor creation",
    "correct_answer": "B",
    "explanation": "MI01 initializes count.",
    "category": "Physical Inventory",
    "difficulty": "easy"
  },
  {
    "question": "What stock type can be sold?",
    "type": "multiple_choice",
    "choice_a": "Blocked",
    "choice_b": "Quality inspection",
    "choice_c": "Unrestricted",
    "choice_d": "Frozen",
    "correct_answer": "C",
    "explanation": "Unrestricted is usable.",
    "category": "Inventory",
    "difficulty": "easy"
  },
  {
    "question": "What stock type needs inspection?",
    "type": "multiple_choice",
    "choice_a": "Unrestricted",
    "choice_b": "Blocked",
    "choice_c": "Quality inspection",
    "choice_d": "Deleted",
    "correct_answer": "C",
    "explanation": "Needs checking first.",
    "category": "Inventory",
    "difficulty": "easy"
  },
  {
    "question": "What stock type cannot be used?",
    "type": "multiple_choice",
    "choice_a": "Unrestricted",
    "choice_b": "Blocked",
    "choice_c": "Quality",
    "choice_d": "Free stock",
    "correct_answer": "B",
    "explanation": "Blocked stock is unusable.",
    "category": "Inventory",
    "difficulty": "easy"
  },
  {
    "question": "What affects forecasting?",
    "type": "multiple_choice",
    "choice_a": "Storage location",
    "choice_b": "Seasonal changes",
    "choice_c": "Vendor code",
    "choice_d": "Movement type",
    "correct_answer": "B",
    "explanation": "Season affects demand.",
    "category": "Planning",
    "difficulty": "easy"
  },
  {
    "question": "What is the purpose of SAP ERP?",
    "type": "multiple_choice",
    "choice_a": "Store files",
    "choice_b": "Integrate processes",
    "choice_c": "Delete data",
    "choice_d": "Manage only finance",
    "correct_answer": "B",
    "explanation": "ERP connects all modules.",
    "category": "SAP Basics",
    "difficulty": "easy"
  },
  {
    "question": "What is the purpose of a Purchase Info Record?",
    "type": "multiple_choice",
    "choice_a": "Store employee data",
    "choice_b": "Store vendor-material purchasing info",
    "choice_c": "Store invoice data",
    "choice_d": "Store stock data",
    "correct_answer": "B",
    "explanation": "It links vendor and material purchasing details.",
    "category": "SAP MM",
    "difficulty": "medium"
  },
  {
    "question": "What is a source list used for?",
    "type": "multiple_choice",
    "choice_a": "List of employees",
    "choice_b": "List of approved vendors for a material",
    "choice_c": "List of invoices",
    "choice_d": "List of reports",
    "correct_answer": "B",
    "explanation": "It defines allowed sources of supply.",
    "category": "Procurement",
    "difficulty": "medium"
  },
  {
    "question": "What is quota arrangement?",
    "type": "multiple_choice",
    "choice_a": "Vendor deletion",
    "choice_b": "Splitting procurement among vendors",
    "choice_c": "Stock transfer",
    "choice_d": "Invoice posting",
    "correct_answer": "B",
    "explanation": "It distributes orders among vendors.",
    "category": "Procurement",
    "difficulty": "hard"
  },
  {
    "question": "What is a scheduling agreement?",
    "type": "multiple_choice",
    "choice_a": "One-time order",
    "choice_b": "Long-term agreement with delivery schedule",
    "choice_c": "Invoice document",
    "choice_d": "Report",
    "correct_answer": "B",
    "explanation": "It defines delivery schedules over time.",
    "category": "Procurement",
    "difficulty": "medium"
  },
  {
    "question": "What is a contract in SAP MM?",
    "type": "multiple_choice",
    "choice_a": "Temporary document",
    "choice_b": "Long-term agreement with vendor",
    "choice_c": "Inventory report",
    "choice_d": "Invoice file",
    "correct_answer": "B",
    "explanation": "Contracts define long-term terms.",
    "category": "Procurement",
    "difficulty": "medium"
  },
  {
    "question": "What is the purpose of release strategy?",
    "type": "multiple_choice",
    "choice_a": "Delete PO",
    "choice_b": "Approve purchasing documents",
    "choice_c": "Create stock",
    "choice_d": "Transfer materials",
    "correct_answer": "B",
    "explanation": "Release strategy controls approvals.",
    "category": "Procurement",
    "difficulty": "medium"
  },
  {
    "question": "What is a goods movement?",
    "type": "multiple_choice",
    "choice_a": "Vendor creation",
    "choice_b": "Movement of materials in system",
    "choice_c": "Invoice posting",
    "choice_d": "Report generation",
    "correct_answer": "B",
    "explanation": "Goods movement updates stock.",
    "category": "SAP MM",
    "difficulty": "easy"
  },
  {
    "question": "What is movement type?",
    "type": "multiple_choice",
    "choice_a": "Vendor type",
    "choice_b": "Code defining stock movement",
    "choice_c": "Report type",
    "choice_d": "Invoice type",
    "correct_answer": "B",
    "explanation": "Movement types control stock behavior.",
    "category": "SAP MM",
    "difficulty": "easy"
  },
  {
    "question": "What is a reservation in SAP?",
    "type": "multiple_choice",
    "choice_a": "Vendor booking",
    "choice_b": "Stock set aside for future use",
    "choice_c": "Invoice posting",
    "choice_d": "Report creation",
    "correct_answer": "B",
    "explanation": "Reservation allocates stock.",
    "category": "SAP MM",
    "difficulty": "medium"
  },
  {
    "question": "What is batch management?",
    "type": "multiple_choice",
    "choice_a": "Employee tracking",
    "choice_b": "Tracking materials by batch/lot",
    "choice_c": "Vendor tracking",
    "choice_d": "Invoice tracking",
    "correct_answer": "B",
    "explanation": "Used for traceability.",
    "category": "SAP MM",
    "difficulty": "medium"
  },
  {
    "question": "What is valuation class?",
    "type": "multiple_choice",
    "choice_a": "Stock type",
    "choice_b": "Determines accounting posting",
    "choice_c": "Vendor category",
    "choice_d": "Report type",
    "correct_answer": "B",
    "explanation": "Links material to GL account.",
    "category": "SAP MM",
    "difficulty": "hard"
  },
  {
    "question": "What is account determination?",
    "type": "multiple_choice",
    "choice_a": "Vendor selection",
    "choice_b": "Assigning accounts for transactions",
    "choice_c": "Stock counting",
    "choice_d": "Invoice deletion",
    "correct_answer": "B",
    "explanation": "Determines financial postings.",
    "category": "SAP MM",
    "difficulty": "hard"
  },
  {
    "question": "What is a GL account?",
    "type": "multiple_choice",
    "choice_a": "Inventory type",
    "choice_b": "Financial account for postings",
    "choice_c": "Vendor list",
    "choice_d": "Report file",
    "correct_answer": "B",
    "explanation": "Used in accounting integration.",
    "category": "SAP FI/MM",
    "difficulty": "medium"
  },
  {
    "question": "What is the purpose of invoice blocking?",
    "type": "multiple_choice",
    "choice_a": "Delete invoice",
    "choice_b": "Prevent payment due to issues",
    "choice_c": "Create invoice",
    "choice_d": "Transfer invoice",
    "correct_answer": "B",
    "explanation": "Blocks incorrect invoices.",
    "category": "SAP MM",
    "difficulty": "medium"
  },
  {
    "question": "What is tolerance limit in invoice verification?",
    "type": "multiple_choice",
    "choice_a": "Vendor limit",
    "choice_b": "Allowed difference between PO and invoice",
    "choice_c": "Stock limit",
    "choice_d": "Report limit",
    "correct_answer": "B",
    "explanation": "Controls acceptable differences.",
    "category": "SAP MM",
    "difficulty": "hard"
  },
  {
    "question": "What is a material type?",
    "type": "multiple_choice",
    "choice_a": "Vendor type",
    "choice_b": "Classification of materials",
    "choice_c": "Invoice type",
    "choice_d": "Report type",
    "correct_answer": "B",
    "explanation": "Defines material category.",
    "category": "SAP MM",
    "difficulty": "medium"
  },
  {
    "question": "What is a purchasing group?",
    "type": "multiple_choice",
    "choice_a": "Sales team",
    "choice_b": "Buyer or team responsible for procurement",
    "choice_c": "Warehouse team",
    "choice_d": "Finance team",
    "correct_answer": "B",
    "explanation": "Responsible for purchasing.",
    "category": "SAP MM",
    "difficulty": "easy"
  },
  {
    "question": "What is a company code?",
    "type": "multiple_choice",
    "choice_a": "Vendor ID",
    "choice_b": "Legal entity in SAP",
    "choice_c": "Storage location",
    "choice_d": "Report code",
    "correct_answer": "B",
    "explanation": "Represents a legal company.",
    "category": "SAP Basics",
    "difficulty": "medium"
  },
  {
    "question": "What is a client in SAP?",
    "type": "multiple_choice",
    "choice_a": "Customer",
    "choice_b": "Highest organizational level",
    "choice_c": "Vendor",
    "choice_d": "Employee",
    "correct_answer": "B",
    "explanation": "Client is top-level unit.",
    "category": "SAP Basics",
    "difficulty": "medium"
  },
  {
    "question": "What is a document type?",
    "type": "multiple_choice",
    "choice_a": "Vendor type",
    "choice_b": "Defines document characteristics",
    "choice_c": "Stock type",
    "choice_d": "Report type",
    "correct_answer": "B",
    "explanation": "Controls document behavior.",
    "category": "SAP MM",
    "difficulty": "medium"
  },
  {
    "question": "What is the purpose of a Goods Issue?",
    "type": "multiple_choice",
    "choice_a": "Receive goods",
    "choice_b": "Remove stock from inventory",
    "choice_c": "Create invoice",
    "choice_d": "Create vendor",
    "correct_answer": "B",
    "explanation": "Goods issue decreases inventory.",
    "category": "SAP MM",
    "difficulty": "easy"
  },
  {
    "question": "What is the role of inventory management?",
    "type": "multiple_choice",
    "choice_a": "Manage employees",
    "choice_b": "Manage stock levels",
    "choice_c": "Manage vendors",
    "choice_d": "Manage invoices",
    "correct_answer": "B",
    "explanation": "Inventory management tracks materials.",
    "category": "SAP MM",
    "difficulty": "easy"
  },
  {
    "question": "What is a material document?",
    "type": "multiple_choice",
    "choice_a": "Vendor file",
    "choice_b": "Record of goods movement",
    "choice_c": "Invoice file",
    "choice_d": "Employee record",
    "correct_answer": "B",
    "explanation": "Material documents track movements.",
    "category": "SAP MM",
    "difficulty": "easy"
  },
  {
    "question": "What happens when invoice is posted?",
    "type": "multiple_choice",
    "choice_a": "Stock increases",
    "choice_b": "Vendor is paid",
    "choice_c": "Financial record is updated",
    "choice_d": "Material is created",
    "correct_answer": "C",
    "explanation": "Invoice affects accounting.",
    "category": "SAP MM",
    "difficulty": "medium"
  },
  {
    "question": "What is the purpose of warehouse management (WM)?",
    "type": "multiple_choice",
    "choice_a": "Manage HR",
    "choice_b": "Manage storage and movement of goods",
    "choice_c": "Manage finance",
    "choice_d": "Manage vendors",
    "correct_answer": "B",
    "explanation": "WM handles storage.",
    "category": "SAP Modules",
    "difficulty": "easy"
  },
  {
    "question": "What is plant maintenance (PM)?",
    "type": "multiple_choice",
    "choice_a": "Manage stock",
    "choice_b": "Maintain equipment",
    "choice_c": "Manage vendors",
    "choice_d": "Manage invoices",
    "correct_answer": "B",
    "explanation": "PM maintains machines.",
    "category": "SAP Modules",
    "difficulty": "easy"
  },
  {
    "question": "What is quality management (QM)?",
    "type": "multiple_choice",
    "choice_a": "Manage inventory",
    "choice_b": "Inspect product quality",
    "choice_c": "Manage HR",
    "choice_d": "Manage vendors",
    "correct_answer": "B",
    "explanation": "QM checks product quality.",
    "category": "SAP Modules",
    "difficulty": "easy"
  },
  {
    "question": "What is human capital management (HCM)?",
    "type": "multiple_choice",
    "choice_a": "Manage stock",
    "choice_b": "Manage employees",
    "choice_c": "Manage vendors",
    "choice_d": "Manage reports",
    "correct_answer": "B",
    "explanation": "HCM handles workforce.",
    "category": "SAP Modules",
    "difficulty": "easy"
  },
  {
    "question": "What is the purpose of reports in SAP?",
    "type": "multiple_choice",
    "choice_a": "Create materials",
    "choice_b": "Analyze data",
    "choice_c": "Create vendors",
    "choice_d": "Create invoices",
    "correct_answer": "B",
    "explanation": "Reports help decision-making.",
    "category": "SAP Basics",
    "difficulty": "easy"
  },
  {
    "question": "What is system navigation in SAP?",
    "type": "multiple_choice",
    "choice_a": "Creating data",
    "choice_b": "Moving within the system",
    "choice_c": "Deleting data",
    "choice_d": "Posting invoice",
    "correct_answer": "B",
    "explanation": "Navigation helps users access functions.",
    "category": "SAP Basics",
    "difficulty": "easy"
  },
  {
    "question": "What is a supply chain?",
    "type": "multiple_choice",
    "choice_a": "Single process",
    "choice_b": "Network of processes and organizations",
    "choice_c": "Inventory report",
    "choice_d": "Vendor list",
    "correct_answer": "B",
    "explanation": "Supply chain connects processes.",
    "category": "SAP Concepts",
    "difficulty": "medium"
  },
  {
    "question": "What is the role of production planning (PP)?",
    "type": "multiple_choice",
    "choice_a": "Manage HR",
    "choice_b": "Plan and control production",
    "choice_c": "Manage vendors",
    "choice_d": "Manage reports",
    "correct_answer": "B",
    "explanation": "PP handles production.",
    "category": "SAP PP",
    "difficulty": "easy"
  },
  {
    "question": "What is an end-to-end process?",
    "type": "multiple_choice",
    "choice_a": "One-step process",
    "choice_b": "Complete business process flow",
    "choice_c": "Inventory only",
    "choice_d": "Vendor only",
    "correct_answer": "B",
    "explanation": "It covers full process.",
    "category": "SAP Basics",
    "difficulty": "easy"
  },
  {
    "question": "What is real-time processing?",
    "type": "multiple_choice",
    "choice_a": "Delayed data",
    "choice_b": "Immediate data update",
    "choice_c": "Manual update",
    "choice_d": "Old data",
    "correct_answer": "B",
    "explanation": "Data updates instantly.",
    "category": "SAP Basics",
    "difficulty": "easy"
  },
  {
    "question": "What is the purpose of a storage location?",
    "type": "multiple_choice",
    "choice_a": "Store employees",
    "choice_b": "Store materials",
    "choice_c": "Store invoices",
    "choice_d": "Store reports",
    "correct_answer": "B",
    "explanation": "Storage location holds stock.",
    "category": "SAP MM",
    "difficulty": "easy"
  },
  {
    "question": "What is a plant in SAP?",
    "type": "multiple_choice",
    "choice_a": "Vendor",
    "choice_b": "Location where operations occur",
    "choice_c": "Report",
    "choice_d": "Invoice",
    "correct_answer": "B",
    "explanation": "Plant is operational unit.",
    "category": "SAP MM",
    "difficulty": "medium"
  },
  {
    "question": "What is stock transfer?",
    "type": "multiple_choice",
    "choice_a": "Delete stock",
    "choice_b": "Move stock between locations",
    "choice_c": "Create stock",
    "choice_d": "Block stock",
    "correct_answer": "B",
    "explanation": "Stock is moved internally.",
    "category": "SAP MM",
    "difficulty": "medium"
  },
  {
    "question": "What is a delivery document?",
    "type": "multiple_choice",
    "choice_a": "Vendor file",
    "choice_b": "Document for goods shipment",
    "choice_c": "Invoice file",
    "choice_d": "Inventory file",
    "correct_answer": "B",
    "explanation": "Delivery handles shipping.",
    "category": "SAP MM",
    "difficulty": "medium"
  },
  {
    "question": "What is a purchasing organization?",
    "type": "multiple_choice",
    "choice_a": "Sales unit",
    "choice_b": "Unit responsible for procurement",
    "choice_c": "Storage unit",
    "choice_d": "Finance unit",
    "correct_answer": "B",
    "explanation": "It handles purchasing.",
    "category": "SAP MM",
    "difficulty": "medium"
  },
  {
    "question": "What is a Purchase Requisition (PR)?",
    "type": "multiple_choice",
    "choice_a": "External document to vendor",
    "choice_b": "Internal request for materials",
    "choice_c": "Invoice document",
    "choice_d": "Delivery document",
    "correct_answer": "B",
    "explanation": "PR is an internal request.",
    "category": "Procurement",
    "difficulty": "easy"
  },
  {
    "question": "What is the purpose of a Purchase Order (PO)?",
    "type": "multiple_choice",
    "choice_a": "Record stock",
    "choice_b": "Request goods from vendor",
    "choice_c": "Create invoice",
    "choice_d": "Track delivery",
    "correct_answer": "B",
    "explanation": "PO is sent to vendor.",
    "category": "Procurement",
    "difficulty": "easy"
  },
  {
    "question": "What happens after Goods Receipt?",
    "type": "multiple_choice",
    "choice_a": "PR is created",
    "choice_b": "Stock is updated",
    "choice_c": "Vendor is deleted",
    "choice_d": "PO is canceled",
    "correct_answer": "B",
    "explanation": "GR updates inventory.",
    "category": "SAP MM",
    "difficulty": "easy"
  },
  {
    "question": "What is the 3-way match in SAP?",
    "type": "multiple_choice",
    "choice_a": "PR, Vendor, Stock",
    "choice_b": "PO, GR, Invoice",
    "choice_c": "Material, Vendor, Plant",
    "choice_d": "Stock, Report, Invoice",
    "correct_answer": "B",
    "explanation": "Invoice is matched with PO and GR.",
    "category": "SAP MM",
    "difficulty": "medium"
  },
  {
    "question": "What is the function of MIGO 561?",
    "type": "multiple_choice",
    "choice_a": "Reverse stock",
    "choice_b": "Add initial stock",
    "choice_c": "Delete stock",
    "choice_d": "Transfer stock",
    "correct_answer": "B",
    "explanation": "561 adds stock.",
    "category": "Movement Types",
    "difficulty": "easy"
  },
  {
    "question": "What is the function of MIGO 562?",
    "type": "multiple_choice",
    "choice_a": "Add stock",
    "choice_b": "Reverse stock entry",
    "choice_c": "Transfer stock",
    "choice_d": "Block stock",
    "correct_answer": "B",
    "explanation": "562 reverses 561.",
    "category": "Movement Types",
    "difficulty": "easy"
  },
  {
    "question": "What is a material master?",
    "type": "multiple_choice",
    "choice_a": "Temporary data",
    "choice_b": "Permanent material record",
    "choice_c": "Vendor record",
    "choice_d": "Report",
    "correct_answer": "B",
    "explanation": "Material master stores material info.",
    "category": "Master Data",
    "difficulty": "easy"
  },
  {
    "question": "What is a vendor master?",
    "type": "multiple_choice",
    "choice_a": "Employee data",
    "choice_b": "Supplier information",
    "choice_c": "Customer data",
    "choice_d": "Inventory data",
    "correct_answer": "B",
    "explanation": "Vendor master stores supplier info.",
    "category": "Master Data",
    "difficulty": "easy"
  },
  {
    "question": "What is meant by unrestricted stock?",
    "type": "multiple_choice",
    "choice_a": "Cannot be used",
    "choice_b": "Available for use and sale",
    "choice_c": "Under inspection",
    "choice_d": "Blocked",
    "correct_answer": "B",
    "explanation": "It is usable stock.",
    "category": "Inventory",
    "difficulty": "easy"
  },
  {
    "question": "What is the purpose of MI01?",
    "type": "multiple_choice",
    "choice_a": "Invoice posting",
    "choice_b": "Inventory count initialization",
    "choice_c": "Goods receipt",
    "choice_d": "PO creation",
    "correct_answer": "B",
    "explanation": "MI01 starts inventory count.",
    "category": "Physical Inventory",
    "difficulty": "easy"
  },
  {
    "question": "What is the role of SAP in business?",
    "type": "multiple_choice",
    "choice_a": "Separate departments",
    "choice_b": "Integrate processes",
    "choice_c": "Delete data",
    "choice_d": "Manage only HR",
    "correct_answer": "B",
    "explanation": "SAP integrates processes.",
    "category": "SAP Basics",
    "difficulty": "easy"
  },
  {
    "question": "What is customization?",
    "type": "multiple_choice",
    "choice_a": "Using standard SAP only",
    "choice_b": "Modifying SAP for gaps",
    "choice_c": "Reporting",
    "choice_d": "Stock counting",
    "correct_answer": "B",
    "explanation": "Customization handles gaps.",
    "category": "SAP Concepts",
    "difficulty": "medium"
  },
  {
    "question": "What is a bottleneck?",
    "type": "multiple_choice",
    "choice_a": "Fast process",
    "choice_b": "Delay due to limited resources",
    "choice_c": "Inventory increase",
    "choice_d": "Vendor issue",
    "correct_answer": "B",
    "explanation": "Bottlenecks slow production.",
    "category": "Planning",
    "difficulty": "medium"
  },
  {
    "question": "What is JIT?",
    "type": "multiple_choice",
    "choice_a": "Extra inventory",
    "choice_b": "Produce when needed",
    "choice_c": "Delay production",
    "choice_d": "Delete stock",
    "correct_answer": "B",
    "explanation": "JIT reduces excess stock.",
    "category": "Planning",
    "difficulty": "easy"
  },
  {
    "question": "What is Kanban?",
    "type": "multiple_choice",
    "choice_a": "Invoice",
    "choice_b": "Signal system for stock",
    "choice_c": "Report",
    "choice_d": "Vendor",
    "correct_answer": "B",
    "explanation": "Kanban signals restock.",
    "category": "Planning",
    "difficulty": "easy"
  }
]
